flask_resty_swagger/__init__.py
flask_resty_swagger-0.2.1.data/scripts/flask-resty-swagger
flask_resty_swagger-0.2.1.dist-info/METADATA
flask_resty_swagger-0.2.1.dist-info/RECORD
flask_resty_swagger-0.2.1.dist-info/WHEEL
flask_resty_swagger-0.2.1.dist-info/top_level.txt
